desugar/__init__.py
desugar/builtins.py
desugar-0.dist-info/LICENSE
desugar-0.dist-info/WHEEL
desugar-0.dist-info/METADATA
desugar-0.dist-info/RECORD
